.bumpversion.cfg
.gitignore
.landscape.yaml
.pre-commit-config.yaml
.readthedocs.yml
.stickler.yml
CHANGELOG.md
LICENSE.txt
MANIFEST.in
README.md
RELEASING.md
changelog.rst
pyproject.toml
requirements.txt
setup.cfg
setup.py
.github/workflows/ci.yaml
.github/workflows/deploy-sdist.yaml
bin/pygac-convert-patmosx-coefficients
bin/pygac-run
continuous_integration/environment.yaml
doc/Makefile
doc/rtd_environment.yaml
doc/source/api.rst
doc/source/conf.py
doc/source/index.rst
doc/source/installation.rst
doc/source/introduction.rst
doc/source/legacy.rst
doc/source/methods.rst
doc/source/usage.rst
doc/source/_static/.gitkeep
doc/source/images/noaa_class_preferences.png
etc/pygac.cfg
etc/pygac.cfg.template
etc/pygac.cfg~
gapfilled_tles/TLE_metop02.txt
gapfilled_tles/TLE_metop02.txt.new
gapfilled_tles/TLE_metopB.txt
gapfilled_tles/TLE_metopa.txt
gapfilled_tles/TLE_metopb.txt
gapfilled_tles/TLE_noaa05.txt
gapfilled_tles/TLE_noaa06.txt
gapfilled_tles/TLE_noaa07.txt
gapfilled_tles/TLE_noaa08.txt
gapfilled_tles/TLE_noaa09.txt
gapfilled_tles/TLE_noaa10.txt
gapfilled_tles/TLE_noaa11.txt
gapfilled_tles/TLE_noaa11_old.txt
gapfilled_tles/TLE_noaa12.txt
gapfilled_tles/TLE_noaa13.txt
gapfilled_tles/TLE_noaa14.txt
gapfilled_tles/TLE_noaa14.txt~
gapfilled_tles/TLE_noaa15.orig
gapfilled_tles/TLE_noaa15.txt
gapfilled_tles/TLE_noaa15.txt.1
gapfilled_tles/TLE_noaa15.txt_old
gapfilled_tles/TLE_noaa15.txt~
gapfilled_tles/TLE_noaa16.txt
gapfilled_tles/TLE_noaa17.txt
gapfilled_tles/TLE_noaa18.txt
gapfilled_tles/TLE_noaa19.txt
gapfilled_tles/TLE_noaa6.txt
gapfilled_tles/TLE_noaa7.txt
gapfilled_tles/TLE_noaa8.txt
gapfilled_tles/TLE_noaa9.txt
gapfilled_tles/TLE_tirosn.txt
gapfilled_tles/noaa-06.txt
gapfilled_tles/noaa-06.zip
gapfilled_tles/noaa-08.txt
gapfilled_tles/noaa-08.zip
gapfilled_tles/tiros-n.txt
gapfilled_tles/tiros-n.zip
pygac/__init__.py
pygac/calibration.py
pygac/clock_offsets_converter.py
pygac/configuration.py
pygac/correct_tsm_issue.py
pygac/gac_calibration.py_old
pygac/gac_io.py
pygac.egg-info/PKG-INFO
pygac.egg-info/SOURCES.txt
pygac.egg-info/dependency_links.txt
pygac.egg-info/not-zip-safe
pygac.egg-info/requires.txt
pygac.egg-info/top_level.txt
