Metadata-Version: 2.1
Name: pygac
Version: 1.7.3
Summary: NOAA AVHRR GAC/LAC reader and calibration
Home-page: https://github.com/pytroll/pygac
Author: The Pytroll Team
Author-email: pytroll@googlegroups.com
License: GPLv3
Classifier: Development Status :: 4 - Beta
Classifier: Intended Audience :: Science/Research
Classifier: License :: OSI Approved :: GNU General Public License v3 or later (GPLv3+)
Classifier: Operating System :: OS Independent
Classifier: Programming Language :: Python
Classifier: Topic :: Scientific/Engineering
Requires-Python: >=3.8
License-File: LICENSE.txt
Requires-Dist: docutils>=0.3
Requires-Dist: numpy>=1.8.0
Requires-Dist: pyorbital>=v0.3.2
Requires-Dist: h5py>=2.0.1
Requires-Dist: scipy>=0.8.0
Requires-Dist: python-geotiepoints>=1.1.8
Requires-Dist: bottleneck>=1.0.0
Provides-Extra: dev
Requires-Dist: pytest; extra == "dev"
Requires-Dist: pre-commit; extra == "dev"
Requires-Dist: flake8; extra == "dev"
